sshifted/EditorMenuSystem.py
sshifted/KeyboardShortcutsDialog.py
sshifted/__init__.py
sshifted/__main__.py
sshifted/settings_dialog.py
sshifted/tree.jpg
sshifted/Library/__init__.py
sshifted/Library/editor.py
sshifted/Library/editor_handler.py
sshifted/ace/ace_keys.html
sshifted/ace/editor.html
sshifted/ace/editor_custom.js
sshifted/ace/qcstuff.js
sshifted/ace/qtchan.js
sshifted/ace/splash.html
sshifted/ace/tree.jpg
sshifted/ace/css/ace.css
sshifted/ace/css/ambiance-1.png
sshifted/ace/css/ambiance-2.png
sshifted/ace/css/ambiance-3.png
sshifted/ace/css/chrome-1.png
sshifted/ace/css/chrome-2.png
sshifted/ace/css/cloud9_day-1.png
sshifted/ace/css/cloud9_day-2.png
sshifted/ace/css/cloud9_night-1.png
sshifted/ace/css/cloud9_night-2.png
sshifted/ace/css/cloud9_night_low_color-1.png
sshifted/ace/css/cloud9_night_low_color-2.png
sshifted/ace/css/clouds-1.png
sshifted/ace/css/clouds-2.png
sshifted/ace/css/clouds_midnight-1.png
sshifted/ace/css/clouds_midnight-2.png
sshifted/ace/css/cobalt-1.png
sshifted/ace/css/cobalt-2.png
sshifted/ace/css/crimson_editor-1.png
sshifted/ace/css/crimson_editor-2.png
sshifted/ace/css/dawn-1.png
sshifted/ace/css/dawn-2.png
sshifted/ace/css/dracula-1.png
sshifted/ace/css/dracula-2.png
sshifted/ace/css/dreamweaver-1.png
sshifted/ace/css/dreamweaver-2.png
sshifted/ace/css/eclipse-1.png
sshifted/ace/css/eclipse-2.png
sshifted/ace/css/github-1.png
sshifted/ace/css/github-2.png
sshifted/ace/css/github_dark-1.png
sshifted/ace/css/github_dark-2.png
sshifted/ace/css/gob-1.png
sshifted/ace/css/gob-2.png
sshifted/ace/css/gruvbox-1.png
sshifted/ace/css/gruvbox-2.png
sshifted/ace/css/gruvbox_dark_hard-1.png
sshifted/ace/css/gruvbox_light_hard-1.png
sshifted/ace/css/gruvbox_light_hard-2.png
sshifted/ace/css/idle_fingers-1.png
sshifted/ace/css/idle_fingers-2.png
sshifted/ace/css/iplastic-1.png
sshifted/ace/css/iplastic-2.png
sshifted/ace/css/iplastic-3.png
sshifted/ace/css/katzenmilch-1.png
sshifted/ace/css/katzenmilch-2.png
sshifted/ace/css/kr_theme-1.png
sshifted-0.3.0.dist-info/LICENSE
sshifted-0.3.0.dist-info/METADATA
sshifted-0.3.0.dist-info/WHEEL
sshifted-0.3.0.dist-info/entry_points.txt
sshifted-0.3.0.dist-info/top_level.txt
sshifted-0.3.0.dist-info/RECORD
