Metadata-Version: 2.1
Name: sshifted
Version: 0.3.0
Summary: A PyQt6 multi-tabbed editor based on Ace.js
Home-page: https://github.com/scottpeterman/sshifted
Author: Scott Peterman
Author-email: scottpeterman@gmail.com
License: GPLv3
Platform: UNKNOWN
Classifier: Programming Language :: Python :: 3.9
Classifier: License :: OSI Approved :: GNU General Public License v3 (GPLv3)
Classifier: Operating System :: OS Independent
License-File: LICENSE
Requires-Dist: PyQt6 >=6.6.1
Requires-Dist: PyQt6-Qt6 >=6.6.1
Requires-Dist: PyQt6-sip >=13.6.0
Requires-Dist: PyQt6-WebEngine >=6.6.0
Requires-Dist: PyQt6-WebEngine-Qt6 >=6.6.1
Requires-Dist: PyYAML >=6.0.1
